pycraftx/__init__.py
pycraftx/engine.py
pycraftx/nexus.py
pycraftx/runner.py
pycraftx/toolkit.py
pycraftx-0.1.0.dist-info/METADATA
pycraftx-0.1.0.dist-info/WHEEL
pycraftx-0.1.0.dist-info/top_level.txt
pycraftx-0.1.0.dist-info/RECORD
